{
 "custom_fields": [
  {
   "_assign": null,
   "_comments": null,
   "_liked_by": null,
   "_user_tags": null,
   "allow_in_quick_entry": 0,
   "allow_on_submit": 0,
   "bold": 0,
   "collapsible": 0,
   "collapsible_depends_on": null,
   "columns": 0,
   "creation": "2024-08-20 14:40:11.651434",
   "default": null,
   "depends_on": null,
   "description": null,
   "docstatus": 0,
   "dt": "Sales Invoice Item",
   "fetch_from": "item_tax_template.custom_zatca_item_tax_category",
   "fetch_if_empty": 0,
   "fieldname": "custom_zatca_item_tax_category",
   "fieldtype": "Select",
   "hidden": 0,
   "hide_border": 0,
   "hide_days": 0,
   "hide_seconds": 0,
   "idx": 44,
   "ignore_user_permissions": 0,
   "ignore_xss_filter": 0,
   "in_global_search": 0,
   "in_list_view": 0,
   "in_preview": 0,
   "in_standard_filter": 0,
   "insert_after": "item_tax_template",
   "is_system_generated": 0,
   "is_virtual": 0,
   "label": "ZATCA Item Tax Category",
   "length": 0,
   "link_filters": null,
   "mandatory_depends_on": null,
   "modified": "2024-08-20 14:40:11.651434",
   "modified_by": "Administrator",
   "module": null,
   "name": "Sales Invoice Item-custom_zatca_item_tax_category",
   "no_copy": 0,
   "non_negative": 0,
   "options": "\nStandard rate\nServices outside scope of tax / Not subject to VAT || {manual entry}\nExempt from Tax || Financial services mentioned in Article 29 of the VAT Regulations\nExempt from Tax || Life insurance services mentioned in Article 29 of the VAT Regulations\nExempt from Tax || Real estate transactions mentioned in Article 30 of the VAT Regulations\nExempt from Tax || Qualified Supply of Goods in Duty Free area\nZero rated goods || Export of goods\nZero rated goods || Export of services\nZero rated goods || The international transport of Goods\nZero rated goods || International transport of passengers\nZero rated goods || Services directly connected and incidental to a Supply of international passenger transport\nZero rated goods || Supply of a qualifying means of transport\nZero rated goods || Any services relating to Goods or passenger transportation as defined in article twenty five of these Regulations\nZero rated goods || Medicines and medical equipment\nZero rated goods || Qualifying metals\nZero rated goods || Private education to citizen\nZero rated goods || Private healthcare to citizen\nZero rated goods || Supply of qualified military goods",
   "owner": "Administrator",
   "parent": null,
   "parentfield": null,
   "parenttype": null,
   "permlevel": 0,
   "placeholder": null,
   "precision": "",
   "print_hide": 0,
   "print_hide_if_no_value": 0,
   "print_width": null,
   "read_only": 1,
   "read_only_depends_on": null,
   "report_hide": 0,
   "reqd": 0,
   "search_index": 0,
   "show_dashboard": 0,
   "sort_options": 0,
   "translatable": 1,
   "unique": 0,
   "width": null
  },
  {
   "_assign": null,
   "_comments": null,
   "_liked_by": null,
   "_user_tags": null,
   "allow_in_quick_entry": 0,
   "allow_on_submit": 0,
   "bold": 0,
   "collapsible": 0,
   "collapsible_depends_on": null,
   "columns": 0,
   "creation": "2022-07-20 13:05:31.594604",
   "default": null,
   "depends_on": null,
   "description": null,
   "docstatus": 0,
   "dt": "Sales Invoice Item",
   "fetch_from": null,
   "fetch_if_empty": 0,
   "fieldname": "delivery_date",
   "fieldtype": "Date",
   "hidden": 0,
   "hide_border": 0,
   "hide_days": 0,
   "hide_seconds": 0,
   "idx": 6,
   "ignore_user_permissions": 0,
   "ignore_xss_filter": 0,
   "in_global_search": 0,
   "in_list_view": 0,
   "in_preview": 0,
   "in_standard_filter": 0,
   "insert_after": "item_name",
   "is_system_generated": 1,
   "is_virtual": 0,
   "label": "Delivery Date",
   "length": 0,
   "link_filters": null,
   "mandatory_depends_on": null,
   "modified": "2022-07-24 22:18:48.434133",
   "modified_by": "Administrator",
   "module": null,
   "name": "Sales Invoice Item-delivery_date",
   "no_copy": 0,
   "non_negative": 0,
   "options": null,
   "owner": "Administrator",
   "parent": null,
   "parentfield": null,
   "parenttype": null,
   "permlevel": 0,
   "placeholder": null,
   "precision": "",
   "print_hide": 1,
   "print_hide_if_no_value": 0,
   "print_width": null,
   "read_only": 0,
   "read_only_depends_on": null,
   "report_hide": 0,
   "reqd": 0,
   "search_index": 0,
   "show_dashboard": 0,
   "sort_options": 0,
   "translatable": 0,
   "unique": 0,
   "width": null
  },
  {
   "_assign": null,
   "_comments": null,
   "_liked_by": null,
   "_user_tags": null,
   "allow_in_quick_entry": 0,
   "allow_on_submit": 0,
   "bold": 0,
   "collapsible": 0,
   "collapsible_depends_on": null,
   "columns": 0,
   "creation": "2022-07-20 13:05:31.956075",
   "default": null,
   "depends_on": null,
   "description": null,
   "docstatus": 0,
   "dt": "Sales Invoice Item",
   "fetch_from": "item_code.is_exempt",
   "fetch_if_empty": 0,
   "fieldname": "is_exempt",
   "fieldtype": "Check",
   "hidden": 0,
   "hide_border": 0,
   "hide_days": 0,
   "hide_seconds": 0,
   "idx": 11,
   "ignore_user_permissions": 0,
   "ignore_xss_filter": 0,
   "in_global_search": 0,
   "in_list_view": 0,
   "in_preview": 0,
   "in_standard_filter": 0,
   "insert_after": "is_zero_rated",
   "is_system_generated": 1,
   "is_virtual": 0,
   "label": "Is Exempt",
   "length": 0,
   "link_filters": null,
   "mandatory_depends_on": null,
   "modified": "2023-07-06 00:03:24.805535",
   "modified_by": "Administrator",
   "module": null,
   "name": "Sales Invoice Item-is_exempt",
   "no_copy": 0,
   "non_negative": 0,
   "options": null,
   "owner": "Administrator",
   "parent": null,
   "parentfield": null,
   "parenttype": null,
   "permlevel": 0,
   "placeholder": null,
   "precision": "",
   "print_hide": 1,
   "print_hide_if_no_value": 0,
   "print_width": null,
   "read_only": 0,
   "read_only_depends_on": null,
   "report_hide": 0,
   "reqd": 0,
   "search_index": 0,
   "show_dashboard": 0,
   "sort_options": 0,
   "translatable": 0,
   "unique": 0,
   "width": null
  },
  {
   "_assign": null,
   "_comments": null,
   "_liked_by": null,
   "_user_tags": null,
   "allow_in_quick_entry": 0,
   "allow_on_submit": 0,
   "bold": 0,
   "collapsible": 0,
   "collapsible_depends_on": null,
   "columns": 0,
   "creation": "2022-07-20 13:05:31.787434",
   "default": null,
   "depends_on": null,
   "description": null,
   "docstatus": 0,
   "dt": "Sales Invoice Item",
   "fetch_from": "item_code.is_zero_rated",
   "fetch_if_empty": 0,
   "fieldname": "is_zero_rated",
   "fieldtype": "Check",
   "hidden": 0,
   "hide_border": 0,
   "hide_days": 0,
   "hide_seconds": 0,
   "idx": 10,
   "ignore_user_permissions": 0,
   "ignore_xss_filter": 0,
   "in_global_search": 0,
   "in_list_view": 0,
   "in_preview": 0,
   "in_standard_filter": 0,
   "insert_after": "description",
   "is_system_generated": 1,
   "is_virtual": 0,
   "label": "Is Zero Rated",
   "length": 0,
   "link_filters": null,
   "mandatory_depends_on": null,
   "modified": "2023-07-06 00:03:24.780444",
   "modified_by": "Administrator",
   "module": null,
   "name": "Sales Invoice Item-is_zero_rated",
   "no_copy": 0,
   "non_negative": 0,
   "options": null,
   "owner": "Administrator",
   "parent": null,
   "parentfield": null,
   "parenttype": null,
   "permlevel": 0,
   "placeholder": null,
   "precision": "",
   "print_hide": 1,
   "print_hide_if_no_value": 0,
   "print_width": null,
   "read_only": 0,
   "read_only_depends_on": null,
   "report_hide": 0,
   "reqd": 0,
   "search_index": 0,
   "show_dashboard": 0,
   "sort_options": 0,
   "translatable": 0,
   "unique": 0,
   "width": null
  },
  {
   "_assign": null,
   "_comments": null,
   "_liked_by": null,
   "_user_tags": null,
   "allow_in_quick_entry": 0,
   "allow_on_submit": 0,
   "bold": 0,
   "collapsible": 0,
   "collapsible_depends_on": null,
   "columns": 0,
   "creation": "2022-01-19 13:52:39.082024",
   "default": null,
   "depends_on": null,
   "description": "\u0631\u0642\u0645 \u0627\u0644\u062e\u0637",
   "docstatus": 0,
   "dt": "Sales Invoice Item",
   "fetch_from": null,
   "fetch_if_empty": 0,
   "fieldname": "line_no",
   "fieldtype": "Data",
   "hidden": 0,
   "hide_border": 0,
   "hide_days": 0,
   "hide_seconds": 0,
   "idx": 4,
   "ignore_user_permissions": 0,
   "ignore_xss_filter": 0,
   "in_global_search": 0,
   "in_list_view": 0,
   "in_preview": 0,
   "in_standard_filter": 0,
   "insert_after": "item_name",
   "is_system_generated": 1,
   "is_virtual": 0,
   "label": "Line No",
   "length": 0,
   "link_filters": null,
   "mandatory_depends_on": null,
   "modified": "2022-01-19 13:52:39.082024",
   "modified_by": "Administrator",
   "module": null,
   "name": "Sales Invoice Item-line_no",
   "no_copy": 0,
   "non_negative": 0,
   "options": null,
   "owner": "Administrator",
   "parent": null,
   "parentfield": null,
   "parenttype": null,
   "permlevel": 0,
   "placeholder": null,
   "precision": "",
   "print_hide": 0,
   "print_hide_if_no_value": 0,
   "print_width": null,
   "read_only": 0,
   "read_only_depends_on": null,
   "report_hide": 0,
   "reqd": 0,
   "search_index": 0,
   "show_dashboard": 0,
   "sort_options": 0,
   "translatable": 1,
   "unique": 0,
   "width": null
  },
  {
   "_assign": null,
   "_comments": null,
   "_liked_by": null,
   "_user_tags": null,
   "allow_in_quick_entry": 0,
   "allow_on_submit": 0,
   "bold": 0,
   "collapsible": 0,
   "collapsible_depends_on": null,
   "columns": 0,
   "creation": "2024-12-17 23:42:20.355852",
   "default": null,
   "depends_on": null,
   "description": null,
   "docstatus": 0,
   "dt": "Sales Invoice Item",
   "fetch_from": null,
   "fetch_if_empty": 0,
   "fieldname": "posa_delivery_date",
   "fieldtype": "Date",
   "hidden": 0,
   "hide_border": 0,
   "hide_days": 0,
   "hide_seconds": 0,
   "idx": 8,
   "ignore_user_permissions": 0,
   "ignore_xss_filter": 0,
   "in_global_search": 0,
   "in_list_view": 0,
   "in_preview": 0,
   "in_standard_filter": 0,
   "insert_after": "posa_row_id",
   "is_system_generated": 0,
   "is_virtual": 0,
   "label": "Delivery Date",
   "length": 0,
   "link_filters": null,
   "mandatory_depends_on": null,
   "modified": "2021-06-21 15:40:02.062423",
   "modified_by": "Administrator",
   "module": null,
   "name": "Sales Invoice Item-posa_delivery_date",
   "no_copy": 0,
   "non_negative": 0,
   "options": null,
   "owner": "Administrator",
   "parent": null,
   "parentfield": null,
   "parenttype": null,
   "permlevel": 0,
   "placeholder": null,
   "precision": "",
   "print_hide": 0,
   "print_hide_if_no_value": 0,
   "print_width": null,
   "read_only": 0,
   "read_only_depends_on": null,
   "report_hide": 0,
   "reqd": 0,
   "search_index": 0,
   "show_dashboard": 0,
   "sort_options": 0,
   "translatable": 0,
   "unique": 0,
   "width": null
  },
  {
   "_assign": null,
   "_comments": null,
   "_liked_by": null,
   "_user_tags": null,
   "allow_in_quick_entry": 0,
   "allow_on_submit": 0,
   "bold": 0,
   "collapsible": 0,
   "collapsible_depends_on": null,
   "columns": 0,
   "creation": "2024-12-17 23:42:40.458265",
   "default": null,
   "depends_on": null,
   "description": null,
   "docstatus": 0,
   "dt": "Sales Invoice Item",
   "fetch_from": null,
   "fetch_if_empty": 0,
   "fieldname": "posa_is_offer",
   "fieldtype": "Check",
   "hidden": 0,
   "hide_border": 0,
   "hide_days": 0,
   "hide_seconds": 0,
   "idx": 54,
   "ignore_user_permissions": 0,
   "ignore_xss_filter": 0,
   "in_global_search": 0,
   "in_list_view": 1,
   "in_preview": 0,
   "in_standard_filter": 0,
   "insert_after": "posa_offer_applied",
   "is_system_generated": 0,
   "is_virtual": 0,
   "label": "Is Offer",
   "length": 0,
   "link_filters": null,
   "mandatory_depends_on": null,
   "modified": "2021-06-12 00:14:20.894553",
   "modified_by": "Administrator",
   "module": null,
   "name": "Sales Invoice Item-posa_is_offer",
   "no_copy": 0,
   "non_negative": 0,
   "options": null,
   "owner": "Administrator",
   "parent": null,
   "parentfield": null,
   "parenttype": null,
   "permlevel": 0,
   "placeholder": null,
   "precision": "",
   "print_hide": 0,
   "print_hide_if_no_value": 0,
   "print_width": null,
   "read_only": 1,
   "read_only_depends_on": null,
   "report_hide": 0,
   "reqd": 0,
   "search_index": 0,
   "show_dashboard": 0,
   "sort_options": 0,
   "translatable": 0,
   "unique": 0,
   "width": null
  },
  {
   "_assign": null,
   "_comments": null,
   "_liked_by": null,
   "_user_tags": null,
   "allow_in_quick_entry": 0,
   "allow_on_submit": 0,
   "bold": 0,
   "collapsible": 0,
   "collapsible_depends_on": null,
   "columns": 0,
   "creation": "2024-12-17 23:42:41.220460",
   "default": null,
   "depends_on": "",
   "description": null,
   "docstatus": 0,
   "dt": "Sales Invoice Item",
   "fetch_from": null,
   "fetch_if_empty": 0,
   "fieldname": "posa_is_replace",
   "fieldtype": "Data",
   "hidden": 0,
   "hide_border": 0,
   "hide_days": 0,
   "hide_seconds": 0,
   "idx": 55,
   "ignore_user_permissions": 0,
   "ignore_xss_filter": 0,
   "in_global_search": 0,
   "in_list_view": 0,
   "in_preview": 0,
   "in_standard_filter": 0,
   "insert_after": "posa_is_offer",
   "is_system_generated": 0,
   "is_virtual": 0,
   "label": "Is Offer Replace For item Row ID",
   "length": 0,
   "link_filters": null,
   "mandatory_depends_on": null,
   "modified": "2021-06-17 18:10:36.233226",
   "modified_by": "Administrator",
   "module": null,
   "name": "Sales Invoice Item-posa_is_replace",
   "no_copy": 0,
   "non_negative": 0,
   "options": null,
   "owner": "Administrator",
   "parent": null,
   "parentfield": null,
   "parenttype": null,
   "permlevel": 0,
   "placeholder": null,
   "precision": "",
   "print_hide": 0,
   "print_hide_if_no_value": 0,
   "print_width": null,
   "read_only": 1,
   "read_only_depends_on": null,
   "report_hide": 0,
   "reqd": 0,
   "search_index": 0,
   "show_dashboard": 0,
   "sort_options": 0,
   "translatable": 1,
   "unique": 0,
   "width": null
  },
  {
   "_assign": null,
   "_comments": null,
   "_liked_by": null,
   "_user_tags": null,
   "allow_in_quick_entry": 0,
   "allow_on_submit": 0,
   "bold": 0,
   "collapsible": 0,
   "collapsible_depends_on": null,
   "columns": 0,
   "creation": "2024-12-17 23:42:19.137516",
   "default": null,
   "depends_on": null,
   "description": null,
   "docstatus": 0,
   "dt": "Sales Invoice Item",
   "fetch_from": null,
   "fetch_if_empty": 0,
   "fieldname": "posa_notes",
   "fieldtype": "Small Text",
   "hidden": 0,
   "hide_border": 0,
   "hide_days": 0,
   "hide_seconds": 0,
   "idx": 4,
   "ignore_user_permissions": 0,
   "ignore_xss_filter": 0,
   "in_global_search": 0,
   "in_list_view": 0,
   "in_preview": 0,
   "in_standard_filter": 0,
   "insert_after": "item_code",
   "is_system_generated": 0,
   "is_virtual": 0,
   "label": "Additional Notes",
   "length": 0,
   "link_filters": null,
   "mandatory_depends_on": null,
   "modified": "2021-06-21 15:28:50.283526",
   "modified_by": "Administrator",
   "module": null,
   "name": "Sales Invoice Item-posa_notes",
   "no_copy": 0,
   "non_negative": 0,
   "options": null,
   "owner": "Administrator",
   "parent": null,
   "parentfield": null,
   "parenttype": null,
   "permlevel": 0,
   "placeholder": null,
   "precision": "",
   "print_hide": 0,
   "print_hide_if_no_value": 0,
   "print_width": null,
   "read_only": 0,
   "read_only_depends_on": null,
   "report_hide": 0,
   "reqd": 0,
   "search_index": 0,
   "show_dashboard": 0,
   "sort_options": 0,
   "translatable": 1,
   "unique": 0,
   "width": null
  },
  {
   "_assign": null,
   "_comments": null,
   "_liked_by": null,
   "_user_tags": null,
   "allow_in_quick_entry": 0,
   "allow_on_submit": 0,
   "bold": 0,
   "collapsible": 0,
   "collapsible_depends_on": null,
   "columns": 0,
   "creation": "2024-12-17 23:42:39.722261",
   "default": null,
   "depends_on": null,
   "description": null,
   "docstatus": 0,
   "dt": "Sales Invoice Item",
   "fetch_from": null,
   "fetch_if_empty": 0,
   "fieldname": "posa_offer_applied",
   "fieldtype": "Check",
   "hidden": 0,
   "hide_border": 0,
   "hide_days": 0,
   "hide_seconds": 0,
   "idx": 53,
   "ignore_user_permissions": 0,
   "ignore_xss_filter": 0,
   "in_global_search": 0,
   "in_list_view": 0,
   "in_preview": 0,
   "in_standard_filter": 0,
   "insert_after": "posa_offers",
   "is_system_generated": 0,
   "is_virtual": 0,
   "label": "Offer Applied",
   "length": 0,
   "link_filters": null,
   "mandatory_depends_on": null,
   "modified": "2021-06-12 00:12:28.473489",
   "modified_by": "Administrator",
   "module": null,
   "name": "Sales Invoice Item-posa_offer_applied",
   "no_copy": 0,
   "non_negative": 0,
   "options": null,
   "owner": "Administrator",
   "parent": null,
   "parentfield": null,
   "parenttype": null,
   "permlevel": 0,
   "placeholder": null,
   "precision": "",
   "print_hide": 0,
   "print_hide_if_no_value": 0,
   "print_width": null,
   "read_only": 1,
   "read_only_depends_on": null,
   "report_hide": 0,
   "reqd": 0,
   "search_index": 0,
   "show_dashboard": 0,
   "sort_options": 0,
   "translatable": 0,
   "unique": 0,
   "width": null
  },
  {
   "_assign": null,
   "_comments": null,
   "_liked_by": null,
   "_user_tags": null,
   "allow_in_quick_entry": 0,
   "allow_on_submit": 0,
   "bold": 0,
   "collapsible": 0,
   "collapsible_depends_on": null,
   "columns": 0,
   "creation": "2024-12-17 23:42:38.857156",
   "default": null,
   "depends_on": null,
   "description": null,
   "docstatus": 0,
   "dt": "Sales Invoice Item",
   "fetch_from": null,
   "fetch_if_empty": 0,
   "fieldname": "posa_offers",
   "fieldtype": "Small Text",
   "hidden": 0,
   "hide_border": 0,
   "hide_days": 0,
   "hide_seconds": 0,
   "idx": 52,
   "ignore_user_permissions": 0,
   "ignore_xss_filter": 0,
   "in_global_search": 0,
   "in_list_view": 0,
   "in_preview": 0,
   "in_standard_filter": 0,
   "insert_after": "pricing_rules",
   "is_system_generated": 0,
   "is_virtual": 0,
   "label": "POS Offers",
   "length": 0,
   "link_filters": null,
   "mandatory_depends_on": null,
   "modified": "2021-06-07 01:51:16.390447",
   "modified_by": "Administrator",
   "module": null,
   "name": "Sales Invoice Item-posa_offers",
   "no_copy": 0,
   "non_negative": 0,
   "options": null,
   "owner": "Administrator",
   "parent": null,
   "parentfield": null,
   "parenttype": null,
   "permlevel": 0,
   "placeholder": null,
   "precision": "",
   "print_hide": 0,
   "print_hide_if_no_value": 0,
   "print_width": null,
   "read_only": 1,
   "read_only_depends_on": null,
   "report_hide": 0,
   "reqd": 0,
   "search_index": 0,
   "show_dashboard": 0,
   "sort_options": 0,
   "translatable": 1,
   "unique": 0,
   "width": null
  },
  {
   "_assign": null,
   "_comments": null,
   "_liked_by": null,
   "_user_tags": null,
   "allow_in_quick_entry": 0,
   "allow_on_submit": 0,
   "bold": 0,
   "collapsible": 0,
   "collapsible_depends_on": null,
   "columns": 0,
   "creation": "2024-12-17 23:42:19.868678",
   "default": null,
   "depends_on": null,
   "description": null,
   "docstatus": 0,
   "dt": "Sales Invoice Item",
   "fetch_from": null,
   "fetch_if_empty": 0,
   "fieldname": "posa_row_id",
   "fieldtype": "Data",
   "hidden": 0,
   "hide_border": 0,
   "hide_days": 0,
   "hide_seconds": 0,
   "idx": 7,
   "ignore_user_permissions": 0,
   "ignore_xss_filter": 0,
   "in_global_search": 0,
   "in_list_view": 0,
   "in_preview": 0,
   "in_standard_filter": 0,
   "insert_after": "item_name",
   "is_system_generated": 0,
   "is_virtual": 0,
   "label": "Row ID",
   "length": 0,
   "link_filters": null,
   "mandatory_depends_on": null,
   "modified": "2021-06-08 17:56:45.705775",
   "modified_by": "Administrator",
   "module": null,
   "name": "Sales Invoice Item-posa_row_id",
   "no_copy": 0,
   "non_negative": 0,
   "options": null,
   "owner": "Administrator",
   "parent": null,
   "parentfield": null,
   "parenttype": null,
   "permlevel": 0,
   "placeholder": null,
   "precision": "",
   "print_hide": 0,
   "print_hide_if_no_value": 0,
   "print_width": null,
   "read_only": 1,
   "read_only_depends_on": null,
   "report_hide": 0,
   "reqd": 0,
   "search_index": 0,
   "show_dashboard": 0,
   "sort_options": 0,
   "translatable": 1,
   "unique": 0,
   "width": null
  },
  {
   "_assign": null,
   "_comments": null,
   "_liked_by": null,
   "_user_tags": null,
   "allow_in_quick_entry": 0,
   "allow_on_submit": 0,
   "bold": 0,
   "collapsible": 0,
   "collapsible_depends_on": null,
   "columns": 0,
   "creation": "2024-10-02 10:27:30.266106",
   "default": null,
   "depends_on": null,
   "description": null,
   "docstatus": 0,
   "dt": "Sales Invoice Item",
   "fetch_from": null,
   "fetch_if_empty": 0,
   "fieldname": "tax_amount",
   "fieldtype": "Currency",
   "hidden": 0,
   "hide_border": 0,
   "hide_days": 0,
   "hide_seconds": 0,
   "idx": 46,
   "ignore_user_permissions": 0,
   "ignore_xss_filter": 0,
   "in_global_search": 0,
   "in_list_view": 0,
   "in_preview": 0,
   "in_standard_filter": 0,
   "insert_after": "tax_rate",
   "is_system_generated": 0,
   "is_virtual": 0,
   "label": "Tax Amount",
   "length": 0,
   "link_filters": null,
   "mandatory_depends_on": null,
   "modified": "2024-10-02 10:27:30.266106",
   "modified_by": "Administrator",
   "module": null,
   "name": "Sales Invoice Item-tax_amount",
   "no_copy": 0,
   "non_negative": 0,
   "options": "currency",
   "owner": "Administrator",
   "parent": null,
   "parentfield": null,
   "parenttype": null,
   "permlevel": 0,
   "placeholder": null,
   "precision": "",
   "print_hide": 1,
   "print_hide_if_no_value": 0,
   "print_width": null,
   "read_only": 1,
   "read_only_depends_on": null,
   "report_hide": 0,
   "reqd": 0,
   "search_index": 0,
   "show_dashboard": 0,
   "sort_options": 0,
   "translatable": 0,
   "unique": 0,
   "width": null
  },
  {
   "_assign": null,
   "_comments": null,
   "_liked_by": null,
   "_user_tags": null,
   "allow_in_quick_entry": 0,
   "allow_on_submit": 1,
   "bold": 0,
   "collapsible": 0,
   "collapsible_depends_on": null,
   "columns": 0,
   "creation": "2022-07-20 13:05:31.070867",
   "default": null,
   "depends_on": null,
   "description": null,
   "docstatus": 0,
   "dt": "Sales Invoice Item",
   "fetch_from": "item_code.tax_code",
   "fetch_if_empty": 0,
   "fieldname": "tax_code",
   "fieldtype": "Read Only",
   "hidden": 0,
   "hide_border": 0,
   "hide_days": 0,
   "hide_seconds": 0,
   "idx": 12,
   "ignore_user_permissions": 0,
   "ignore_xss_filter": 0,
   "in_global_search": 0,
   "in_list_view": 0,
   "in_preview": 0,
   "in_standard_filter": 0,
   "insert_after": "is_exempt",
   "is_system_generated": 1,
   "is_virtual": 0,
   "label": "Tax Code",
   "length": 0,
   "link_filters": null,
   "mandatory_depends_on": null,
   "modified": "2022-07-24 22:18:46.882727",
   "modified_by": "Administrator",
   "module": null,
   "name": "Sales Invoice Item-tax_code",
   "no_copy": 0,
   "non_negative": 0,
   "options": null,
   "owner": "Administrator",
   "parent": null,
   "parentfield": null,
   "parenttype": null,
   "permlevel": 0,
   "placeholder": null,
   "precision": "",
   "print_hide": 1,
   "print_hide_if_no_value": 0,
   "print_width": null,
   "read_only": 0,
   "read_only_depends_on": null,
   "report_hide": 0,
   "reqd": 0,
   "search_index": 0,
   "show_dashboard": 0,
   "sort_options": 0,
   "translatable": 0,
   "unique": 0,
   "width": null
  },
  {
   "_assign": null,
   "_comments": null,
   "_liked_by": null,
   "_user_tags": null,
   "allow_in_quick_entry": 0,
   "allow_on_submit": 0,
   "bold": 0,
   "collapsible": 0,
   "collapsible_depends_on": null,
   "columns": 0,
   "creation": "2024-10-02 10:27:30.102219",
   "default": null,
   "depends_on": null,
   "description": null,
   "docstatus": 0,
   "dt": "Sales Invoice Item",
   "fetch_from": null,
   "fetch_if_empty": 0,
   "fieldname": "tax_rate",
   "fieldtype": "Float",
   "hidden": 0,
   "hide_border": 0,
   "hide_days": 0,
   "hide_seconds": 0,
   "idx": 45,
   "ignore_user_permissions": 0,
   "ignore_xss_filter": 0,
   "in_global_search": 0,
   "in_list_view": 0,
   "in_preview": 0,
   "in_standard_filter": 0,
   "insert_after": "custom_zatca_item_tax_category",
   "is_system_generated": 0,
   "is_virtual": 0,
   "label": "Tax Rate",
   "length": 0,
   "link_filters": null,
   "mandatory_depends_on": null,
   "modified": "2024-10-02 10:27:30.102219",
   "modified_by": "Administrator",
   "module": null,
   "name": "Sales Invoice Item-tax_rate",
   "no_copy": 0,
   "non_negative": 0,
   "options": null,
   "owner": "Administrator",
   "parent": null,
   "parentfield": null,
   "parenttype": null,
   "permlevel": 0,
   "placeholder": null,
   "precision": "",
   "print_hide": 1,
   "print_hide_if_no_value": 0,
   "print_width": null,
   "read_only": 1,
   "read_only_depends_on": null,
   "report_hide": 0,
   "reqd": 0,
   "search_index": 0,
   "show_dashboard": 0,
   "sort_options": 0,
   "translatable": 0,
   "unique": 0,
   "width": null
  },
  {
   "_assign": null,
   "_comments": null,
   "_liked_by": null,
   "_user_tags": null,
   "allow_in_quick_entry": 0,
   "allow_on_submit": 0,
   "bold": 0,
   "collapsible": 0,
   "collapsible_depends_on": null,
   "columns": 0,
   "creation": "2024-10-02 10:27:30.269835",
   "default": null,
   "depends_on": null,
   "description": null,
   "docstatus": 0,
   "dt": "Sales Invoice Item",
   "fetch_from": null,
   "fetch_if_empty": 0,
   "fieldname": "total_amount",
   "fieldtype": "Currency",
   "hidden": 0,
   "hide_border": 0,
   "hide_days": 0,
   "hide_seconds": 0,
   "idx": 47,
   "ignore_user_permissions": 0,
   "ignore_xss_filter": 0,
   "in_global_search": 0,
   "in_list_view": 0,
   "in_preview": 0,
   "in_standard_filter": 0,
   "insert_after": "tax_amount",
   "is_system_generated": 0,
   "is_virtual": 0,
   "label": "Total Amount",
   "length": 0,
   "link_filters": null,
   "mandatory_depends_on": null,
   "modified": "2024-10-02 10:27:30.269835",
   "modified_by": "Administrator",
   "module": null,
   "name": "Sales Invoice Item-total_amount",
   "no_copy": 0,
   "non_negative": 0,
   "options": "currency",
   "owner": "Administrator",
   "parent": null,
   "parentfield": null,
   "parenttype": null,
   "permlevel": 0,
   "placeholder": null,
   "precision": "",
   "print_hide": 1,
   "print_hide_if_no_value": 0,
   "print_width": null,
   "read_only": 1,
   "read_only_depends_on": null,
   "report_hide": 0,
   "reqd": 0,
   "search_index": 0,
   "show_dashboard": 0,
   "sort_options": 0,
   "translatable": 0,
   "unique": 0,
   "width": null
  }
 ],
 "custom_perms": [],
 "doctype": "Sales Invoice Item",
 "links": [],
 "property_setters": [
  {
   "_assign": null,
   "_comments": null,
   "_liked_by": null,
   "_user_tags": null,
   "creation": "2024-12-17 23:58:25.819495",
   "default_value": null,
   "doc_type": "Sales Invoice Item",
   "docstatus": 0,
   "doctype_or_field": "DocField",
   "field_name": "barcode",
   "idx": 0,
   "is_system_generated": 1,
   "modified": "2024-12-17 23:58:25.819495",
   "modified_by": "Administrator",
   "module": null,
   "name": "Sales Invoice Item-barcode-hidden",
   "owner": "Administrator",
   "parent": null,
   "parentfield": null,
   "parenttype": null,
   "property": "hidden",
   "property_type": "Check",
   "row_name": null,
   "value": "1"
  },
  {
   "_assign": null,
   "_comments": null,
   "_liked_by": null,
   "_user_tags": null,
   "creation": "2023-07-26 13:16:07.441907",
   "default_value": null,
   "doc_type": "Sales Invoice Item",
   "docstatus": 0,
   "doctype_or_field": "DocField",
   "field_name": "discount_account",
   "idx": 0,
   "is_system_generated": 0,
   "modified": "2024-12-14 01:12:27.931094",
   "modified_by": "Administrator",
   "module": null,
   "name": "Sales Invoice Item-discount_account-default",
   "owner": "Administrator",
   "parent": null,
   "parentfield": null,
   "parenttype": null,
   "property": "default",
   "property_type": "Text",
   "row_name": null,
   "value": ""
  },
  {
   "_assign": null,
   "_comments": null,
   "_liked_by": null,
   "_user_tags": null,
   "creation": "2024-12-19 22:44:51.036854",
   "default_value": null,
   "doc_type": "Sales Invoice Item",
   "docstatus": 0,
   "doctype_or_field": "DocField",
   "field_name": "discount_account",
   "idx": 0,
   "is_system_generated": 0,
   "modified": "2024-12-19 22:44:51.036854",
   "modified_by": "eslam_salah@upcmails.com",
   "module": null,
   "name": "Sales Invoice Item-discount_account-hidden",
   "owner": "eslam_salah@upcmails.com",
   "parent": null,
   "parentfield": null,
   "parenttype": null,
   "property": "hidden",
   "property_type": "Check",
   "row_name": null,
   "value": "1"
  },
  {
   "_assign": null,
   "_comments": null,
   "_liked_by": null,
   "_user_tags": null,
   "creation": "2024-12-19 22:44:51.066339",
   "default_value": null,
   "doc_type": "Sales Invoice Item",
   "docstatus": 0,
   "doctype_or_field": "DocField",
   "field_name": "discount_account",
   "idx": 0,
   "is_system_generated": 0,
   "modified": "2024-12-19 22:44:51.066339",
   "modified_by": "eslam_salah@upcmails.com",
   "module": null,
   "name": "Sales Invoice Item-discount_account-mandatory_depends_on",
   "owner": "eslam_salah@upcmails.com",
   "parent": null,
   "parentfield": null,
   "parenttype": null,
   "property": "mandatory_depends_on",
   "property_type": "Code",
   "row_name": null,
   "value": ""
  },
  {
   "_assign": null,
   "_comments": null,
   "_liked_by": null,
   "_user_tags": null,
   "creation": "2024-12-19 20:28:40.066629",
   "default_value": null,
   "doc_type": "Sales Invoice Item",
   "docstatus": 0,
   "doctype_or_field": "DocType",
   "field_name": null,
   "idx": 0,
   "is_system_generated": 0,
   "modified": "2024-12-19 20:28:40.066629",
   "modified_by": "Administrator",
   "module": null,
   "name": "Sales Invoice Item-main-field_order",
   "owner": "Administrator",
   "parent": null,
   "parentfield": null,
   "parenttype": null,
   "property": "field_order",
   "property_type": "Data",
   "row_name": null,
   "value": "[\"barcode\", \"has_item_scanned\", \"item_code\", \"posa_notes\", \"col_break1\", \"item_name\", \"posa_row_id\", \"posa_delivery_date\", \"delivery_date\", \"line_no\", \"customer_item_code\", \"description_section\", \"description\", \"is_zero_rated\", \"is_exempt\", \"tax_code\", \"item_group\", \"brand\", \"image_section\", \"image\", \"image_view\", \"quantity_and_rate\", \"qty\", \"stock_uom\", \"col_break2\", \"uom\", \"conversion_factor\", \"stock_qty\", \"section_break_17\", \"price_list_rate\", \"base_price_list_rate\", \"discount_and_margin\", \"margin_type\", \"margin_rate_or_amount\", \"rate_with_margin\", \"column_break_19\", \"discount_percentage\", \"discount_amount\", \"base_rate_with_margin\", \"section_break1\", \"rate\", \"amount\", \"item_tax_template\", \"custom_zatca_item_tax_category\", \"tax_rate\", \"tax_amount\", \"total_amount\", \"col_break3\", \"base_rate\", \"base_amount\", \"pricing_rules\", \"posa_offers\", \"posa_offer_applied\", \"posa_is_offer\", \"posa_is_replace\", \"stock_uom_rate\", \"is_free_item\", \"grant_commission\", \"section_break_21\", \"net_rate\", \"net_amount\", \"column_break_24\", \"base_net_rate\", \"base_net_amount\", \"drop_ship\", \"delivered_by_supplier\", \"accounting\", \"income_account\", \"is_fixed_asset\", \"asset\", \"finance_book\", \"col_break4\", \"expense_account\", \"discount_account\", \"deferred_revenue\", \"deferred_revenue_account\", \"service_stop_date\", \"enable_deferred_revenue\", \"column_break_50\", \"service_start_date\", \"service_end_date\", \"section_break_18\", \"weight_per_unit\", \"total_weight\", \"column_break_21\", \"weight_uom\", \"warehouse_and_reference\", \"warehouse\", \"target_warehouse\", \"quality_inspection\", \"pick_serial_and_batch\", \"serial_and_batch_bundle\", \"use_serial_batch_fields\", \"col_break5\", \"allow_zero_valuation_rate\", \"incoming_rate\", \"item_tax_rate\", \"actual_batch_qty\", \"actual_qty\", \"column_break_ogff\", \"company_total_stock\", \"section_break_eoec\", \"serial_no\", \"column_break_ytgd\", \"batch_no\", \"available_quantity_section\", \"edit_references\", \"sales_order\", \"so_detail\", \"sales_invoice_item\", \"column_break_74\", \"delivery_note\", \"dn_detail\", \"delivered_qty\", \"internal_transfer_section\", \"purchase_order\", \"column_break_92\", \"purchase_order_item\", \"accounting_dimensions_section\", \"cost_center\", \"dimension_col_break\", \"project\", \"section_break_54\", \"page_break\"]"
  },
  {
   "_assign": null,
   "_comments": null,
   "_liked_by": null,
   "_user_tags": null,
   "creation": "2024-12-17 23:58:26.267427",
   "default_value": null,
   "doc_type": "Sales Invoice Item",
   "docstatus": 0,
   "doctype_or_field": "DocField",
   "field_name": "target_warehouse",
   "idx": 0,
   "is_system_generated": 0,
   "modified": "2024-12-17 23:58:26.267427",
   "modified_by": "Administrator",
   "module": null,
   "name": "Sales Invoice Item-target_warehouse-hidden",
   "owner": "Administrator",
   "parent": null,
   "parentfield": null,
   "parenttype": null,
   "property": "hidden",
   "property_type": "Check",
   "row_name": null,
   "value": "1"
  }
 ],
 "sync_on_migrate": 1
}